[
    {
        "attacks": [
            {
                "convertedEnergyCost": 1,
                "cost": [
                    "Psychic"
                ],
                "damage": "10",
                "name": "Всплеск",
                "text": ""
            }
        ],
        "convertedRetreatCost": 1,
        "evolvesFrom": "",
        "hp": 60,
        "id": "tk6a-1",
        "name": "Spoink",
        "number": "1",
        "rarity": "Common",
        "resistances": [],
        "retreatCost": [
            "Colorless"
        ],
        "setCode": "tk6a",
        "subtype": "Basic",
        "supertype": "Pokémon",
        "types": [
            "Psychic"
        ],
        "weaknesses": [
            {
                "type": "Psychic",
                "value": "×2"
            }
        ]
    },
    {
        "attacks": [
            {
                "convertedEnergyCost": 1,
                "cost": [
                    "Psychic"
                ],
                "damage": "",
                "name": "Зловещий Голос",
                "text": "Положи 2 фишки урона на каждого из Покемона твоего противника."
            },
            {
                "convertedEnergyCost": 2,
                "cost": [
                    "Psychic",
                    "Psychic"
                ],
                "damage": "",
                "name": "Завывание Духа",
                "text": "Клади фишки урона на обоих активных Покемона, пока ОЖ каждого из Покемона не уменьшится до 10."
            }
        ],
        "convertedRetreatCost": 2,
        "evolvesFrom": "Pumpkaboo",
        "hp": 100,
        "id": "tk6a-2",
        "name": "Гургайст",
        "number": "2",
        "rarity": "Rare",
        "resistances": [
            {
                "type": "Fighting",
                "value": "-20"
            }
        ],
        "retreatCost": [
            "Colorless",
            "Colorless"
        ],
        "setCode": "tk6a",
        "subtype": "Stage 1",
        "supertype": "Pokémon",
        "types": [
            "Psychic"
        ],
        "weaknesses": [
            {
                "type": "Darkness",
                "value": "×2"
            }
        ]
    },
    {
        "attacks": [
            {
                "convertedEnergyCost": 1,
                "cost": [
                    "Colorless"
                ],
                "damage": "20",
                "name": "Желудочный Сок",
                "text": "Защищающийся Покемон не может использовать свои Таланты до конца твоего следующего хода."
            },
            {
                "convertedEnergyCost": 3,
                "cost": [
                    "Psychic",
                    "Colorless",
                    "Colorless"
                ],
                "damage": "50",
                "name": "Ядовитый Укол",
                "text": "Активный Покемон твоего противника теперь отравлен."
            }
        ],
        "convertedRetreatCost": 1,
        "evolvesFrom": "Ekans",
        "hp": 90,
        "id": "tk6a-3",
        "name": "Арбок",
        "number": "3",
        "rarity": "Rare",
        "resistances": [],
        "retreatCost": [
            "Colorless"
        ],
        "setCode": "tk6a",
        "subtype": "Stage 1",
        "supertype": "Pokémon",
        "types": [
            "Psychic"
        ],
        "weaknesses": [
            {
                "type": "Psychic",
                "value": "×2"
            }
        ]
    },
    {
        "attacks": [
            {
                "convertedEnergyCost": 2,
                "cost": [
                    "Colorless",
                    "Colorless"
                ],
                "damage": "20",
                "name": "Бросок",
                "text": ""
            }
        ],
        "convertedRetreatCost": 1,
        "evolvesFrom": "",
        "hp": 60,
        "id": "tk6a-4",
        "name": "Баннелби",
        "number": "4",
        "rarity": "Common",
        "resistances": [],
        "retreatCost": [
            "Colorless"
        ],
        "setCode": "tk6a",
        "subtype": "Basic",
        "supertype": "Pokémon",
        "types": [
            "Colorless"
        ],
        "weaknesses": [
            {
                "type": "Fighting",
                "value": "×2"
            }
        ]
    },
    {
        "id": "tk6a-5",
        "name": "Энергия Психо",
        "number": "5",
        "rarity": "Common",
        "setCode": "tk6a",
        "subtype": "Basic",
        "supertype": "Energy",
        "text": [
            ""
        ]
    },
    {
        "id": "tk6a-6",
        "name": "Энергия Психо",
        "number": "6",
        "rarity": "Common",
        "setCode": "tk6a",
        "subtype": "Basic",
        "supertype": "Energy",
        "text": [
            ""
        ]
    },
    {
        "id": "tk6a-7",
        "name": "Энергия Психо",
        "number": "7",
        "rarity": "Common",
        "setCode": "tk6a",
        "subtype": "Basic",
        "supertype": "Energy",
        "text": [
            ""
        ]
    },
    {
        "id": "tk6a-8",
        "name": "Энергия Психо",
        "number": "8",
        "rarity": "Common",
        "setCode": "tk6a",
        "subtype": "Basic",
        "supertype": "Energy",
        "text": [
            ""
        ]
    },
    {
        "id": "tk6a-9",
        "name": "Энергия Психо",
        "number": "9",
        "rarity": "Common",
        "setCode": "tk6a",
        "subtype": "Basic",
        "supertype": "Energy",
        "text": [
            ""
        ]
    },
    {
        "id": "tk6a-10",
        "name": "Энергия Психо",
        "number": "10",
        "rarity": "Common",
        "setCode": "tk6a",
        "subtype": "Basic",
        "supertype": "Energy",
        "text": [
            ""
        ]
    },
    {
        "attacks": [
            {
                "convertedEnergyCost": 1,
                "cost": [
                    "Psychic"
                ],
                "damage": "",
                "name": "Луч Замешательства",
                "text": "Активный Покемон твоего противника теперь сбит с толку."
            }
        ],
        "convertedRetreatCost": 2,
        "evolvesFrom": "",
        "hp": 60,
        "id": "tk6a-11",
        "name": "Пампкабу",
        "number": "11",
        "rarity": "Common",
        "resistances": [
            {
                "type": "Fighting",
                "value": "-20"
            }
        ],
        "retreatCost": [
            "Colorless",
            "Colorless"
        ],
        "setCode": "tk6a",
        "subtype": "Basic",
        "supertype": "Pokémon",
        "types": [
            "Psychic"
        ],
        "weaknesses": [
            {
                "type": "Darkness",
                "value": "×2"
            }
        ]
    },
    {
        "attacks": [
            {
                "convertedEnergyCost": 1,
                "cost": [
                    "Colorless"
                ],
                "damage": "",
                "name": "Сверхзвук",
                "text": "Подбрось монетку. Если выпал \"орёл\", Защищающийся Покемон Сбит с Толку."
            },
            {
                "convertedEnergyCost": 3,
                "cost": [
                    "Colorless",
                    "Colorless",
                    "Colorless"
                ],
                "damage": "30",
                "name": "Атака Крылом",
                "text": ""
            }
        ],
        "convertedRetreatCost": 1,
        "evolvesFrom": "",
        "hp": 60,
        "id": "tk6a-12",
        "name": "Нойбат",
        "number": "12",
        "rarity": "Common",
        "resistances": [
            {
                "type": "Fighting",
                "value": "-20"
            }
        ],
        "retreatCost": [
            "Colorless"
        ],
        "setCode": "tk6a",
        "subtype": "Basic",
        "supertype": "Pokémon",
        "types": [
            "Colorless"
        ],
        "weaknesses": [
            {
                "type": "Lightning",
                "value": "×2"
            }
        ]
    },
    {
        "attacks": [
            {
                "convertedEnergyCost": 2,
                "cost": [
                    "Colorless",
                    "Colorless"
                ],
                "damage": "20+",
                "name": "Второй Укус",
                "text": "Эта атака наносит на 10 пунктов урона больше за каждую фишку урона на активном Покемоне твоего противника."
            },
            {
                "convertedEnergyCost": 3,
                "cost": [
                    "Darkness",
                    "Psychic",
                    "Colorless"
                ],
                "damage": "60+",
                "name": "Sonic Bazooka",
                "text": "Flip a coin. If heads, this attack does 30 more damage and your opponent's Active Pokémon is now Confused."
            }
        ],
        "convertedRetreatCost": 1,
        "evolvesFrom": "Noibat",
        "hp": 110,
        "id": "tk6a-13",
        "name": "Нойверн",
        "number": "13",
        "rarity": "Rare",
        "resistances": [],
        "retreatCost": [
            "Colorless"
        ],
        "setCode": "tk6a",
        "subtype": "Stage 1",
        "supertype": "Pokémon",
        "types": [
            "Dragon"
        ],
        "weaknesses": [
            {
                "type": "Fairy",
                "value": "×2"
            }
        ]
    },
    {
        "id": "tk6a-14",
        "name": "Ловец Покемона",
        "number": "14",
        "rarity": "Uncommon",
        "setCode": "tk6a",
        "subtype": "Item",
        "supertype": "Trainer",
        "text": [
            "Брось монету. Если выпал орёл, замени активного Покемона твоего противника на 1 из запасных Покемонов твоего противника."
        ]
    },
    {
        "id": "tk6a-15",
        "name": "Эликсир",
        "number": "15",
        "rarity": "Common",
        "setCode": "tk6a",
        "subtype": "Item",
        "supertype": "Trainer",
        "text": [
            "Один из твоих Покемона излечивает 30 пунктов урона."
        ]
    },
    {
        "attacks": [
            {
                "convertedEnergyCost": 2,
                "cost": [
                    "Colorless",
                    "Colorless"
                ],
                "damage": "20",
                "name": "Укус",
                "text": ""
            }
        ],
        "convertedRetreatCost": 2,
        "evolvesFrom": "",
        "hp": 70,
        "id": "tk6a-16",
        "name": "Эканс",
        "number": "16",
        "rarity": "Common",
        "resistances": [],
        "retreatCost": [
            "Colorless",
            "Colorless"
        ],
        "setCode": "tk6a",
        "subtype": "Basic",
        "supertype": "Pokémon",
        "types": [
            "Psychic"
        ],
        "weaknesses": [
            {
                "type": "Psychic",
                "value": "×2"
            }
        ]
    },
    {
        "id": "tk6a-17",
        "name": "Энергия Психо",
        "number": "17",
        "rarity": "Common",
        "setCode": "tk6a",
        "subtype": "Basic",
        "supertype": "Energy",
        "text": [
            ""
        ]
    },
    {
        "attacks": [
            {
                "convertedEnergyCost": 1,
                "cost": [
                    "Psychic"
                ],
                "damage": "",
                "name": "Луч Замешательства",
                "text": "Активный Покемон твоего противника теперь сбит с толку."
            }
        ],
        "convertedRetreatCost": 2,
        "evolvesFrom": "",
        "hp": 60,
        "id": "tk6a-18",
        "name": "Пампкабу",
        "number": "18",
        "rarity": "Common",
        "resistances": [
            {
                "type": "Fighting",
                "value": "-20"
            }
        ],
        "retreatCost": [
            "Colorless",
            "Colorless"
        ],
        "setCode": "tk6a",
        "subtype": "Basic",
        "supertype": "Pokémon",
        "types": [
            "Psychic"
        ],
        "weaknesses": [
            {
                "type": "Darkness",
                "value": "×2"
            }
        ]
    },
    {
        "id": "tk6a-19",
        "name": "Энергия Тьмы",
        "number": "19",
        "rarity": "Common",
        "setCode": "tk6a",
        "subtype": "Basic",
        "supertype": "Energy",
        "text": [
            ""
        ]
    },
    {
        "attacks": [
            {
                "convertedEnergyCost": 2,
                "cost": [
                    "Colorless",
                    "Colorless"
                ],
                "damage": "20",
                "name": "Крепкие Челюсти",
                "text": "Брось монету. Если выпал орёл, активный Покемон твоего противника теперь парализован."
            },
            {
                "convertedEnergyCost": 3,
                "cost": [
                    "Colorless",
                    "Colorless",
                    "Colorless"
                ],
                "damage": "50",
                "name": "Sharp Fang",
                "text": ""
            }
        ],
        "convertedRetreatCost": 1,
        "evolvesFrom": "",
        "hp": 90,
        "id": "tk6a-20",
        "name": "Фурфу",
        "number": "20",
        "rarity": "Common",
        "resistances": [],
        "retreatCost": [
            "Colorless"
        ],
        "setCode": "tk6a",
        "subtype": "Basic",
        "supertype": "Pokémon",
        "types": [
            "Colorless"
        ],
        "weaknesses": [
            {
                "type": "Fighting",
                "value": "×2"
            }
        ]
    },
    {
        "id": "tk6a-21",
        "name": "ПокеБолл",
        "number": "21",
        "rarity": "Uncommon",
        "setCode": "tk6a",
        "subtype": "Item",
        "supertype": "Trainer",
        "text": [
            "Брось монету. Если выпал орел, найди в своей колоде одного Покемона, открой его и возьми себе в руку. После этого перетасуй колоду."
        ]
    },
    {
        "id": "tk6a-22",
        "name": "Энергия Тьмы",
        "number": "22",
        "rarity": "Common",
        "setCode": "tk6a",
        "subtype": "Basic",
        "supertype": "Energy",
        "text": [
            ""
        ]
    },
    {
        "attacks": [
            {
                "convertedEnergyCost": 1,
                "cost": [
                    "Colorless"
                ],
                "damage": "",
                "name": "Сверхзвук",
                "text": "Подбрось монетку. Если выпал \"орёл\", Защищающийся Покемон Сбит с Толку."
            },
            {
                "convertedEnergyCost": 3,
                "cost": [
                    "Colorless",
                    "Colorless",
                    "Colorless"
                ],
                "damage": "30",
                "name": "Атака Крылом",
                "text": ""
            }
        ],
        "convertedRetreatCost": 1,
        "evolvesFrom": "",
        "hp": 60,
        "id": "tk6a-23",
        "name": "Нойбат",
        "number": "23",
        "rarity": "Common",
        "resistances": [
            {
                "type": "Fighting",
                "value": "-20"
            }
        ],
        "retreatCost": [
            "Colorless"
        ],
        "setCode": "tk6a",
        "subtype": "Basic",
        "supertype": "Pokémon",
        "types": [
            "Colorless"
        ],
        "weaknesses": [
            {
                "type": "Lightning",
                "value": "×2"
            }
        ]
    },
    {
        "id": "tk6a-24",
        "name": "Письмо Профессора",
        "number": "24",
        "rarity": "Uncommon",
        "setCode": "tk6a",
        "subtype": "Item",
        "supertype": "Trainer",
        "text": [
            "Найди в своей колоде до двух карт базовой Энергии, открой их и возьми себе в руку. После этого перетасуй колоду."
        ]
    },
    {
        "id": "tk6a-25",
        "name": "Энергия Психо",
        "number": "25",
        "rarity": "Common",
        "setCode": "tk6a",
        "subtype": "Basic",
        "supertype": "Energy",
        "text": [
            ""
        ]
    },
    {
        "id": "tk6a-26",
        "name": "Энергия Тьмы",
        "number": "26",
        "rarity": "Common",
        "setCode": "tk6a",
        "subtype": "Basic",
        "supertype": "Energy",
        "text": [
            ""
        ]
    },
    {
        "id": "tk6a-27",
        "name": "Эликсир",
        "number": "27",
        "rarity": "Common",
        "setCode": "tk6a",
        "subtype": "Item",
        "supertype": "Trainer",
        "text": [
            "Один из твоих Покемона излечивает 30 пунктов урона."
        ]
    },
    {
        "id": "tk6a-28",
        "name": "Энергия Тьмы",
        "number": "28",
        "rarity": "Common",
        "setCode": "tk6a",
        "subtype": "Basic",
        "supertype": "Energy",
        "text": [
            ""
        ]
    },
    {
        "id": "tk6a-29",
        "name": "Замена",
        "number": "29",
        "rarity": "Common",
        "setCode": "tk6a",
        "subtype": "Item",
        "supertype": "Trainer",
        "text": [
            "Замени своего активного Покемона на одного из своих запасных Покемона."
        ]
    },
    {
        "attacks": [
            {
                "convertedEnergyCost": 2,
                "cost": [
                    "Colorless",
                    "Colorless"
                ],
                "damage": "20+",
                "name": "Второй Укус",
                "text": "Эта атака наносит на 10 пунктов урона больше за каждую фишку урона на активном Покемоне твоего противника."
            },
            {
                "convertedEnergyCost": 3,
                "cost": [
                    "Darkness",
                    "Psychic",
                    "Colorless"
                ],
                "damage": "60+",
                "name": "Sonic Bazooka",
                "text": "Flip a coin. If heads, this attack does 30 more damage and your opponent's Active Pokémon is now Confused."
            }
        ],
        "convertedRetreatCost": 1,
        "evolvesFrom": "Noibat",
        "hp": 110,
        "id": "tk6a-30",
        "name": "Нойверн",
        "number": "30",
        "rarity": "Rare Holo",
        "resistances": [],
        "retreatCost": [
            "Colorless"
        ],
        "setCode": "tk6a",
        "subtype": "Stage 1",
        "supertype": "Pokémon",
        "types": [
            "Dragon"
        ],
        "weaknesses": [
            {
                "type": "Fairy",
                "value": "×2"
            }
        ]
    }
]