[
    {
        "id": "bw_energy-1",
        "name": "Energia Oscurità ",
        "number": "1",
        "rarity": "Common",
        "setCode": "bw_energy",
        "subtype": "Basic",
        "supertype": "Energy",
        "text": [
            ""
        ]
    },
    {
        "id": "bw_energy-3",
        "name": "Energia Lotta",
        "number": "3",
        "rarity": "Common",
        "setCode": "bw_energy",
        "subtype": "Basic",
        "supertype": "Energy",
        "text": [
            ""
        ]
    },
    {
        "id": "bw_energy-4",
        "name": "Energia Fuoco",
        "number": "4",
        "rarity": "Common",
        "setCode": "bw_energy",
        "subtype": "Basic",
        "supertype": "Energy",
        "text": [
            ""
        ]
    },
    {
        "id": "bw_energy-5",
        "name": "Energia Erba",
        "number": "5",
        "rarity": "Common",
        "setCode": "bw_energy",
        "subtype": "Basic",
        "supertype": "Energy",
        "text": [
            ""
        ]
    },
    {
        "id": "bw_energy-6",
        "name": "Energia Lampo",
        "number": "6",
        "rarity": "Common",
        "setCode": "bw_energy",
        "subtype": "Basic",
        "supertype": "Energy",
        "text": [
            ""
        ]
    },
    {
        "id": "bw_energy-7",
        "name": "Energia Metallo",
        "number": "7",
        "rarity": "Common",
        "setCode": "bw_energy",
        "subtype": "Basic",
        "supertype": "Energy",
        "text": [
            ""
        ]
    },
    {
        "id": "bw_energy-8",
        "name": "Energia Psico",
        "number": "8",
        "rarity": "Common",
        "setCode": "bw_energy",
        "subtype": "Basic",
        "supertype": "Energy",
        "text": [
            ""
        ]
    },
    {
        "id": "bw_energy-9",
        "name": "Energia Acqua",
        "number": "9",
        "rarity": "Common",
        "setCode": "bw_energy",
        "subtype": "Basic",
        "supertype": "Energy",
        "text": [
            ""
        ]
    }
]