[
    {
        "id": "tk8b-1",
        "name": "Pflanzen-Energie",
        "number": "1",
        "rarity": "Common",
        "setCode": "tk8b",
        "subtype": "Basic",
        "supertype": "Energy",
        "text": [
            ""
        ]
    },
    {
        "id": "tk8b-2",
        "name": "Pflanzen-Energie",
        "number": "2",
        "rarity": "Common",
        "setCode": "tk8b",
        "subtype": "Basic",
        "supertype": "Energy",
        "text": [
            ""
        ]
    },
    {
        "id": "tk8b-3",
        "name": "Pflanzen-Energie",
        "number": "3",
        "rarity": "Common",
        "setCode": "tk8b",
        "subtype": "Basic",
        "supertype": "Energy",
        "text": [
            ""
        ]
    },
    {
        "attacks": [
            {
                "convertedEnergyCost": 1,
                "cost": [
                    "Colorless"
                ],
                "damage": "10",
                "name": "Schnabel",
                "text": ""
            },
            {
                "convertedEnergyCost": 2,
                "cost": [
                    "Colorless",
                    "Colorless"
                ],
                "damage": "10+",
                "name": "Ruckzuckhieb",
                "text": "Wirf 1 Münze. Bei „Kopf“ fügt dieser Angriff 20 weitere Schadenspunkte zu."
            }
        ],
        "convertedRetreatCost": 1,
        "evolvesFrom": "",
        "hp": 50,
        "id": "tk8b-4",
        "name": "Dartiri",
        "number": "4",
        "rarity": "Common",
        "resistances": [
            {
                "type": "Fighting",
                "value": "-20"
            }
        ],
        "retreatCost": [
            "Colorless"
        ],
        "setCode": "tk8b",
        "subtype": "Basic",
        "supertype": "Pokémon",
        "types": [
            "Colorless"
        ],
        "weaknesses": [
            {
                "type": "Lightning",
                "value": "×2"
            }
        ]
    },
    {
        "id": "tk8b-5",
        "name": "Pflanzen-Energie",
        "number": "5",
        "rarity": "Common",
        "setCode": "tk8b",
        "subtype": "Basic",
        "supertype": "Energy",
        "text": [
            ""
        ]
    },
    {
        "attacks": [
            {
                "convertedEnergyCost": 2,
                "cost": [
                    "Colorless",
                    "Colorless"
                ],
                "damage": "30",
                "name": "Verprügler",
                "text": ""
            },
            {
                "convertedEnergyCost": 1,
                "cost": [
                    "Grass"
                ],
                "damage": "20",
                "name": "Haken",
                "text": ""
            }
        ],
        "convertedRetreatCost": 2,
        "evolvesFrom": "Lotad",
        "hp": 80,
        "id": "tk8b-6",
        "name": "Lombrero",
        "number": "6",
        "rarity": "Uncommon",
        "resistances": [],
        "retreatCost": [
            "Colorless",
            "Colorless"
        ],
        "setCode": "tk8b",
        "subtype": "Stage 1",
        "supertype": "Pokémon",
        "types": [
            "Grass"
        ],
        "weaknesses": [
            {
                "type": "Fire",
                "value": "×2"
            }
        ]
    },
    {
        "attacks": [
            {
                "convertedEnergyCost": 1,
                "cost": [
                    "Grass"
                ],
                "damage": "10+",
                "name": "Ruckzuckhieb",
                "text": "Wirf 1 Münze. Bei „Kopf“ fügt dieser Angriff 10 weitere Schadenspunkte zu."
            }
        ],
        "convertedRetreatCost": 1,
        "evolvesFrom": "",
        "hp": 60,
        "id": "tk8b-7",
        "name": "Geckarbor",
        "number": "7",
        "rarity": "Common",
        "resistances": [],
        "retreatCost": [
            "Colorless"
        ],
        "setCode": "tk8b",
        "subtype": "Basic",
        "supertype": "Pokémon",
        "types": [
            "Grass"
        ],
        "weaknesses": [
            {
                "type": "Fire",
                "value": "×2"
            }
        ]
    },
    {
        "id": "tk8b-8",
        "name": "Psycho-Energie",
        "number": "8",
        "rarity": "Common",
        "setCode": "tk8b",
        "subtype": "Basic",
        "supertype": "Energy",
        "text": [
            ""
        ]
    },
    {
        "id": "tk8b-9",
        "name": "Psycho-Energie",
        "number": "9",
        "rarity": "Common",
        "setCode": "tk8b",
        "subtype": "Basic",
        "supertype": "Energy",
        "text": [
            ""
        ]
    },
    {
        "id": "tk8b-10",
        "name": "Psycho-Energie",
        "number": "10",
        "rarity": "Common",
        "setCode": "tk8b",
        "subtype": "Basic",
        "supertype": "Energy",
        "text": [
            ""
        ]
    },
    {
        "attacks": [
            {
                "convertedEnergyCost": 2,
                "cost": [
                    "Colorless",
                    "Colorless"
                ],
                "damage": "20",
                "name": "Verprügler",
                "text": ""
            }
        ],
        "convertedRetreatCost": 1,
        "evolvesFrom": "",
        "hp": 60,
        "id": "tk8b-11",
        "name": "Loturzel",
        "number": "11",
        "rarity": "Common",
        "resistances": [],
        "retreatCost": [
            "Colorless"
        ],
        "setCode": "tk8b",
        "subtype": "Basic",
        "supertype": "Pokémon",
        "types": [
            "Grass"
        ],
        "weaknesses": [
            {
                "type": "Fire",
                "value": "×2"
            }
        ]
    },
    {
        "attacks": [
            {
                "convertedEnergyCost": 3,
                "cost": [
                    "Grass",
                    "Colorless",
                    "Colorless"
                ],
                "damage": "50",
                "name": "Megasauger",
                "text": "Heile 20 Schadenspunkte bei diesem Pokémon."
            },
            {
                "convertedEnergyCost": 4,
                "cost": [
                    "Grass",
                    "Grass",
                    "Colorless",
                    "Colorless"
                ],
                "damage": "80+",
                "name": "Strauchler",
                "text": "Dieser Angriff fügt 10 weitere Schadenspunkte für jedes {C}-Symbol in den Rückzugskosten des Aktiven Pokémon deines Gegners zu."
            }
        ],
        "convertedRetreatCost": 4,
        "evolvesFrom": "Tangela",
        "hp": 130,
        "id": "tk8b-12",
        "name": "Tangoloss",
        "number": "12",
        "rarity": "Rare",
        "resistances": [],
        "retreatCost": [
            "Colorless",
            "Colorless",
            "Colorless",
            "Colorless"
        ],
        "setCode": "tk8b",
        "subtype": "Stage 1",
        "supertype": "Pokémon",
        "types": [
            "Grass"
        ],
        "weaknesses": [
            {
                "type": "Fire",
                "value": "×2"
            }
        ]
    },
    {
        "attacks": [
            {
                "convertedEnergyCost": 3,
                "cost": [
                    "Grass",
                    "Grass",
                    "Colorless"
                ],
                "damage": "30",
                "name": "Rankenhieb",
                "text": ""
            },
            {
                "convertedEnergyCost": 2,
                "cost": [
                    "Grass",
                    "Colorless"
                ],
                "damage": "20",
                "name": "Absorber",
                "text": "Heile 20 Schadenspunkte bei diesem Pokémon."
            }
        ],
        "convertedRetreatCost": 2,
        "evolvesFrom": "",
        "hp": 80,
        "id": "tk8b-13",
        "name": "Tangela",
        "number": "13",
        "rarity": "Common",
        "resistances": [],
        "retreatCost": [
            "Colorless",
            "Colorless"
        ],
        "setCode": "tk8b",
        "subtype": "Basic",
        "supertype": "Pokémon",
        "types": [
            "Grass"
        ],
        "weaknesses": [
            {
                "type": "Fire",
                "value": "×2"
            }
        ]
    },
    {
        "attacks": [
            {
                "convertedEnergyCost": 3,
                "cost": [
                    "Psychic",
                    "Colorless",
                    "Colorless"
                ],
                "damage": "60+",
                "name": "Psychoprisma",
                "text": "Wirf 1 Münze. Bei „Kopf“ fügt dieser Angriff 20 weitere Schadenspunkte zu."
            },
            {
                "convertedEnergyCost": 1,
                "cost": [
                    "Psychic"
                ],
                "damage": "20",
                "name": "Psychosphäre",
                "text": ""
            }
        ],
        "convertedRetreatCost": 1,
        "evolvesFrom": "",
        "hp": 100,
        "id": "tk8b-14",
        "name": "Latias",
        "number": "14",
        "rarity": "Rare",
        "resistances": [],
        "retreatCost": [
            "Colorless"
        ],
        "setCode": "tk8b",
        "subtype": "Basic",
        "supertype": "Pokémon",
        "types": [
            "Psychic"
        ],
        "weaknesses": [
            {
                "type": "Psychic",
                "value": "×2"
            }
        ]
    },
    {
        "id": "tk8b-15",
        "name": "Trank",
        "number": "15",
        "rarity": "Common",
        "setCode": "tk8b",
        "subtype": "Item",
        "supertype": "Trainer",
        "text": [
            "Heile 30 Schadenspunkte bei 1 deiner Pokémon."
        ]
    },
    {
        "attacks": [
            {
                "convertedEnergyCost": 1,
                "cost": [
                    "Colorless"
                ],
                "damage": "10",
                "name": "Zertrampeln",
                "text": ""
            }
        ],
        "convertedRetreatCost": 1,
        "evolvesFrom": "",
        "hp": 50,
        "id": "tk8b-16",
        "name": "Gehweiher",
        "number": "16",
        "rarity": "Common",
        "resistances": [],
        "retreatCost": [
            "Colorless"
        ],
        "setCode": "tk8b",
        "subtype": "Basic",
        "supertype": "Pokémon",
        "types": [
            "Grass"
        ],
        "weaknesses": [
            {
                "type": "Fire",
                "value": "×2"
            }
        ]
    },
    {
        "id": "tk8b-17",
        "name": "Psycho-Energie",
        "number": "17",
        "rarity": "Common",
        "setCode": "tk8b",
        "subtype": "Basic",
        "supertype": "Energy",
        "text": [
            ""
        ]
    },
    {
        "attacks": [
            {
                "convertedEnergyCost": 1,
                "cost": [
                    "Grass"
                ],
                "damage": "20",
                "name": "Pfund",
                "text": ""
            },
            {
                "convertedEnergyCost": 3,
                "cost": [
                    "Grass",
                    "Colorless",
                    "Colorless"
                ],
                "damage": "40",
                "name": "Agilität",
                "text": "Wirf 1 Münze. Verhindere bei „Kopf“ während des nächsten Zuges deines Gegners alle Effekte von Angriffen, einschließlich Schaden, die diesem Pokémon zugefügt werden."
            }
        ],
        "convertedRetreatCost": 1,
        "evolvesFrom": "Treecko",
        "hp": 80,
        "id": "tk8b-18",
        "name": "Reptain",
        "number": "18",
        "rarity": "Uncommon",
        "resistances": [],
        "retreatCost": [
            "Colorless"
        ],
        "setCode": "tk8b",
        "subtype": "Stage 1",
        "supertype": "Pokémon",
        "types": [
            "Grass"
        ],
        "weaknesses": [
            {
                "type": "Fire",
                "value": "×2"
            }
        ]
    },
    {
        "id": "tk8b-19",
        "name": "Pflanzen-Energie",
        "number": "19",
        "rarity": "Common",
        "setCode": "tk8b",
        "subtype": "Basic",
        "supertype": "Energy",
        "text": [
            ""
        ]
    },
    {
        "id": "tk8b-20",
        "name": "Kunstrad",
        "number": "20",
        "rarity": "Uncommon",
        "setCode": "tk8b",
        "subtype": "Item",
        "supertype": "Trainer",
        "text": [
            "Schau dir die 2 obersten Karten deines Decks an und nimm 1 auf deine Hand. Lege die andere Karte auf deinen Ablagestapel."
        ]
    },
    {
        "attacks": [
            {
                "convertedEnergyCost": 2,
                "cost": [
                    "Colorless",
                    "Colorless"
                ],
                "damage": "30",
                "name": "Verprügler",
                "text": ""
            },
            {
                "convertedEnergyCost": 1,
                "cost": [
                    "Grass"
                ],
                "damage": "20",
                "name": "Haken",
                "text": ""
            }
        ],
        "convertedRetreatCost": 2,
        "evolvesFrom": "Lotad",
        "hp": 80,
        "id": "tk8b-21",
        "name": "Lombrero",
        "number": "21",
        "rarity": "Uncommon",
        "resistances": [],
        "retreatCost": [
            "Colorless",
            "Colorless"
        ],
        "setCode": "tk8b",
        "subtype": "Stage 1",
        "supertype": "Pokémon",
        "types": [
            "Grass"
        ],
        "weaknesses": [
            {
                "type": "Fire",
                "value": "×2"
            }
        ]
    },
    {
        "id": "tk8b-22",
        "name": "Psycho-Energie",
        "number": "22",
        "rarity": "Common",
        "setCode": "tk8b",
        "subtype": "Basic",
        "supertype": "Energy",
        "text": [
            ""
        ]
    },
    {
        "attacks": [
            {
                "convertedEnergyCost": 2,
                "cost": [
                    "Colorless",
                    "Colorless"
                ],
                "damage": "20",
                "name": "Verprügler",
                "text": ""
            }
        ],
        "convertedRetreatCost": 1,
        "evolvesFrom": "",
        "hp": 60,
        "id": "tk8b-23",
        "name": "Loturzel",
        "number": "23",
        "rarity": "Common",
        "resistances": [],
        "retreatCost": [
            "Colorless"
        ],
        "setCode": "tk8b",
        "subtype": "Basic",
        "supertype": "Pokémon",
        "types": [
            "Grass"
        ],
        "weaknesses": [
            {
                "type": "Fire",
                "value": "×2"
            }
        ]
    },
    {
        "attacks": [
            {
                "convertedEnergyCost": 1,
                "cost": [
                    "Grass"
                ],
                "damage": "10+",
                "name": "Ruckzuckhieb",
                "text": "Wirf 1 Münze. Bei „Kopf“ fügt dieser Angriff 10 weitere Schadenspunkte zu."
            }
        ],
        "convertedRetreatCost": 1,
        "evolvesFrom": "",
        "hp": 60,
        "id": "tk8b-24",
        "name": "Geckarbor",
        "number": "24",
        "rarity": "Common",
        "resistances": [],
        "retreatCost": [
            "Colorless"
        ],
        "setCode": "tk8b",
        "subtype": "Basic",
        "supertype": "Pokémon",
        "types": [
            "Grass"
        ],
        "weaknesses": [
            {
                "type": "Fire",
                "value": "×2"
            }
        ]
    },
    {
        "attacks": [
            {
                "convertedEnergyCost": 3,
                "cost": [
                    "Grass",
                    "Colorless",
                    "Colorless"
                ],
                "damage": "50",
                "name": "Megasauger",
                "text": "Heile 20 Schadenspunkte bei diesem Pokémon."
            },
            {
                "convertedEnergyCost": 4,
                "cost": [
                    "Grass",
                    "Grass",
                    "Colorless",
                    "Colorless"
                ],
                "damage": "80+",
                "name": "Strauchler",
                "text": "Dieser Angriff fügt 10 weitere Schadenspunkte für jedes {C}-Symbol in den Rückzugskosten des Aktiven Pokémon deines Gegners zu."
            }
        ],
        "convertedRetreatCost": 4,
        "evolvesFrom": "Tangela",
        "hp": 130,
        "id": "tk8b-25",
        "name": "Tangoloss",
        "number": "25",
        "rarity": "Rare",
        "resistances": [],
        "retreatCost": [
            "Colorless",
            "Colorless",
            "Colorless",
            "Colorless"
        ],
        "setCode": "tk8b",
        "subtype": "Stage 1",
        "supertype": "Pokémon",
        "types": [
            "Grass"
        ],
        "weaknesses": [
            {
                "type": "Fire",
                "value": "×2"
            }
        ]
    },
    {
        "attacks": [
            {
                "convertedEnergyCost": 3,
                "cost": [
                    "Grass",
                    "Grass",
                    "Colorless"
                ],
                "damage": "30",
                "name": "Rankenhieb",
                "text": ""
            },
            {
                "convertedEnergyCost": 2,
                "cost": [
                    "Grass",
                    "Colorless"
                ],
                "damage": "20",
                "name": "Absorber",
                "text": "Heile 20 Schadenspunkte bei diesem Pokémon."
            }
        ],
        "convertedRetreatCost": 2,
        "evolvesFrom": "",
        "hp": 80,
        "id": "tk8b-26",
        "name": "Tangela",
        "number": "26",
        "rarity": "Common",
        "resistances": [],
        "retreatCost": [
            "Colorless",
            "Colorless"
        ],
        "setCode": "tk8b",
        "subtype": "Basic",
        "supertype": "Pokémon",
        "types": [
            "Grass"
        ],
        "weaknesses": [
            {
                "type": "Fire",
                "value": "×2"
            }
        ]
    },
    {
        "attacks": [
            {
                "convertedEnergyCost": 1,
                "cost": [
                    "Grass"
                ],
                "damage": "20",
                "name": "Pfund",
                "text": ""
            },
            {
                "convertedEnergyCost": 3,
                "cost": [
                    "Grass",
                    "Colorless",
                    "Colorless"
                ],
                "damage": "40",
                "name": "Agilität",
                "text": "Wirf 1 Münze. Verhindere bei „Kopf“ während des nächsten Zuges deines Gegners alle Effekte von Angriffen, einschließlich Schaden, die diesem Pokémon zugefügt werden."
            }
        ],
        "convertedRetreatCost": 1,
        "evolvesFrom": "Treecko",
        "hp": 80,
        "id": "tk8b-27",
        "name": "Reptain",
        "number": "27",
        "rarity": "Uncommon",
        "resistances": [],
        "retreatCost": [
            "Colorless"
        ],
        "setCode": "tk8b",
        "subtype": "Stage 1",
        "supertype": "Pokémon",
        "types": [
            "Grass"
        ],
        "weaknesses": [
            {
                "type": "Fire",
                "value": "×2"
            }
        ]
    },
    {
        "id": "tk8b-28",
        "name": "Psycho-Energie",
        "number": "28",
        "rarity": "Common",
        "setCode": "tk8b",
        "subtype": "Basic",
        "supertype": "Energy",
        "text": [
            ""
        ]
    },
    {
        "id": "tk8b-29",
        "name": "Kunstrad",
        "number": "29",
        "rarity": "Uncommon",
        "setCode": "tk8b",
        "subtype": "Item",
        "supertype": "Trainer",
        "text": [
            "Schau dir die 2 obersten Karten deines Decks an und nimm 1 auf deine Hand. Lege die andere Karte auf deinen Ablagestapel."
        ]
    },
    {
        "attacks": [
            {
                "convertedEnergyCost": 3,
                "cost": [
                    "Psychic",
                    "Colorless",
                    "Colorless"
                ],
                "damage": "60+",
                "name": "Psychoprisma",
                "text": "Wirf 1 Münze. Bei „Kopf“ fügt dieser Angriff 20 weitere Schadenspunkte zu."
            },
            {
                "convertedEnergyCost": 1,
                "cost": [
                    "Psychic"
                ],
                "damage": "20",
                "name": "Psychosphäre",
                "text": ""
            }
        ],
        "convertedRetreatCost": 1,
        "evolvesFrom": "",
        "hp": 100,
        "id": "tk8b-30",
        "name": "Latias",
        "number": "30",
        "rarity": "Rare Holo",
        "resistances": [],
        "retreatCost": [
            "Colorless"
        ],
        "setCode": "tk8b",
        "subtype": "Basic",
        "supertype": "Pokémon",
        "types": [
            "Psychic"
        ],
        "weaknesses": [
            {
                "type": "Psychic",
                "value": "×2"
            }
        ]
    }
]